ytspace/__init__.py
ytspace/__main__.py
ytspace/cli.py
ytspace/funcs.py
ytspace/sql_funcs.py
ytspace/yt_funcs.py
ytspace/pytube/__init__.py
ytspace/pytube/__main__.py
ytspace/pytube/captions.py
ytspace/pytube/cipher.py
ytspace/pytube/cli.py
ytspace/pytube/exceptions.py
ytspace/pytube/extract.py
ytspace/pytube/helpers.py
ytspace/pytube/innertube.py
ytspace/pytube/itags.py
ytspace/pytube/metadata.py
ytspace/pytube/monostate.py
ytspace/pytube/parser.py
ytspace/pytube/query.py
ytspace/pytube/request.py
ytspace/pytube/streams.py
ytspace/pytube/version.py
ytspace-14.93.dist-info/LICENSE.txt
ytspace-14.93.dist-info/METADATA
ytspace-14.93.dist-info/WHEEL
ytspace-14.93.dist-info/top_level.txt
ytspace-14.93.dist-info/RECORD
