Metadata-Version: 2.1
Name: ytspace
Version: 14.93
Summary: Python-MySQL project to download YouTube videos and music from terminal using pytube.
Home-page: https://github.com/Yugam4254/YT-Space
Author: Yugam Sehgal
Author-email: yugamsehgal4254@gmail.com
License: UNKNOWN
Platform: UNKNOWN
Classifier: Programming Language :: Python :: 3
Classifier: License :: OSI Approved :: MIT License
Classifier: Operating System :: OS Independent
Requires-Python: >=3.6
Requires-Dist: mysql-connector
